hudpy/__init__.py
hudpy/hud_cache.py
hudpy/hud_chas.py
hudpy/hud_cw.py
hudpy/hud_dataset_cw.py
hudpy/hud_do_query_calls.py
hudpy/hud_download_bar.py
hudpy/hud_fmr.py
hudpy/hud_geo_in_geo.py
hudpy/hud_get_recent_data.py
hudpy/hud_input_check.py
hudpy/hud_internet_online.py
hudpy/hud_key.py
hudpy/hud_misc.py
hudpy/hud_pkg_env.py
hudpy/hud_user.py
hudpy/hud_user_agent.py
hudpy/hud_website_docs.py
tests/__init__.py
tests/test_chas.py
tests/test_cw.py
tests/test_cw_a_dataset.py
tests/test_decomp_chas.py
tests/test_decomp_cw.py
tests/test_decomp_fmr.py
tests/test_fmr.py
tests/test_geo_in_geo.py
tests/test_get_recent_data.py
tests/test_il.py
tests/test_misc.py
hudpy-0.2.0.dist-info/LICENSE
hudpy-0.2.0.dist-info/LICENSE.md
hudpy-0.2.0.dist-info/METADATA
hudpy-0.2.0.dist-info/WHEEL
hudpy-0.2.0.dist-info/top_level.txt
hudpy-0.2.0.dist-info/RECORD
