Metadata-Version: 2.1
Name: hudpy
Version: 0.2.0
Summary: A python interface to the US Department of Housing and Urban Development APIs.
Home-page: https://github.com/etam4260/hudpy
Author: Emmet Tam
Author-email: emmet_tam@yahoo.com
License: UNKNOWN
Project-URL: Bug Tracker, https://github.com/etam4260/hudpy/issues
Platform: UNKNOWN
Classifier: Programming Language :: Python :: 3
Classifier: License :: OSI Approved :: GNU General Public License v2 (GPLv2)
Classifier: Operating System :: OS Independent
Requires-Python: >= 2.6
Requires-Dist: pandas
Requires-Dist: datetime
Requires-Dist: typing
Requires-Dist: urllib3
